cache_me_outside
