Metadata-Version: 1.1
Name: cache-me-outside
Version: 1.0
Summary: A package that makes caching fun! How about that?
Home-page: https://github.com/mdmedley/cache_me_outside
Author: Marcus Medley
Author-email: mdmeds@gmail.com
License: MIT
Keywords: cache,caching,python cache
Platform: UNKNOWN
Classifier: Development Status :: 5 - Production/Stable
Classifier: Intended Audience :: Developers
Classifier: Natural Language :: English
Classifier: License :: OSI Approved :: MIT License
Classifier: Programming Language :: Python :: 2.7
Classifier: Programming Language :: Python :: 3.4
Classifier: Programming Language :: Python :: 3.5
Classifier: Programming Language :: Python :: 3.6
Classifier: Topic :: Software Development :: Libraries
Classifier: Topic :: Software Development :: Libraries :: Python Modules
Classifier: Topic :: Utilities
